setup.cfg
setup.py
src/alexandria/__init__.py
src/alexandria/client.py
src/alexandria/tests.py
src/alexandria/dsl/__init__.py
src/alexandria/dsl/core.py
src/alexandria/dsl/exceptions.py
src/alexandria/dsl/utils.py
src/alexandria/dsl/validators.py
src/alexandria/examples/__init__.py
src/alexandria/examples/demo.py
src/alexandria/examples/devquiz.py
src/alexandria/examples/hivquiz.py
src/alexandria/examples/voting.py
src/alexandria/loader/__init__.py
src/alexandria/loader/base.py
src/alexandria/sessions/__init__.py
src/alexandria/sessions/backend.py
src/alexandria/sessions/manager.py
src/alexandria/sessions/db/__init__.py
src/alexandria/sessions/db/models.py
src/alexandria/sessions/db/settings.py
src/alexandria/sessions/db/tests.py
src/alexandria/sessions/db/urls.py
src/alexandria/sessions/db/views.py
src/alexandria/sessions/db/management/__init__.py
src/alexandria/sessions/db/management/commands/__init__.py
src/alexandria/sessions/db/management/commands/alexandria_export_csv.py
src/alexandria/transport/__init__.py
src/alexandria/transport/ussd.py
src/alexandria/transport/xmpp.py
src/smn_alexandria.egg-info/PKG-INFO
src/smn_alexandria.egg-info/SOURCES.txt
src/smn_alexandria.egg-info/dependency_links.txt
src/smn_alexandria.egg-info/requires.txt
src/smn_alexandria.egg-info/top_level.txt