Metadata-Version: 1.0
Name: smn-alexandria
Version: 0.1.1
Summary: A DSL for interactive, linear, text based menus.
Home-page: http://github.com/smn/alexandria
Author: Simon de Haan
Author-email: UNKNOWN
License: BSD
Platform: UNKNOWN
